seirsplus/FARZ.py
seirsplus/__init__.py
seirsplus/legacy_models.py
seirsplus/models.py
seirsplus/networks.py
seirsplus/sim_loops.py
seirsplus/utilities.py
seirsplus-1.0.7.dist-info/LICENSE
seirsplus-1.0.7.dist-info/METADATA
seirsplus-1.0.7.dist-info/WHEEL
seirsplus-1.0.7.dist-info/top_level.txt
seirsplus-1.0.7.dist-info/RECORD
