Metadata-Version: 2.1
Name: seirsplus
Version: 1.0.7
Summary: Models of SEIRS epidemic dynamics with extensions, including network-structured populations, testing, contact tracing, and social distancing.
Home-page: https://github.com/ryansmcgee/SEIRS-network-model
Author: Ryan Seamus McGee
Author-email: ryansmcgee@gmail.com
License: MIT
Platform: UNKNOWN
Requires-Dist: numpy
Requires-Dist: scipy
Requires-Dist: networkx
